LICENSE.txt
README.md
setup.cfg
setup.py
gmi_utils/__init__.py
gmi_utils/gmi_exception.py
gmi_utils/interval.py
gmi_utils.egg-info/PKG-INFO
gmi_utils.egg-info/SOURCES.txt
gmi_utils.egg-info/dependency_links.txt
gmi_utils.egg-info/top_level.txt