Metadata-Version: 2.1
Name: gmi-utils
Version: 0.1.10
Summary: Utils used by GetMoney Inc.
Home-page: https://github.com/get-money-inc/utils-py
Author: GetMoney Inc.
Author-email: get.money.inc.official@gmail.com
License: UNKNOWN
Platform: UNKNOWN
License-File: LICENSE.txt
